pygyver/__init__.py
pygyver/_version.py
pygyver/etl/__init__.py
pygyver/etl/db.py
pygyver/etl/dw.py
pygyver/etl/facebook.py
pygyver/etl/gooddata.py
pygyver/etl/gs.py
pygyver/etl/lib.py
pygyver/etl/ometria.py
pygyver/etl/pipeline.py
pygyver/etl/prep.py
pygyver/etl/storage.py
pygyver/etl/toolkit.py
pygyver/etl/zendesk.py
pygyver/tools/__init__.py
pygyver/tools/migrator/__init__.py
pygyver/tools/migrator/migrator.py
pygyver/tools/slack_messenger/__init__.py
pygyver/tools/slack_messenger/slack_messenger.py
pygyver-0.1.1.42.dist-info/LICENSE
pygyver-0.1.1.42.dist-info/METADATA
pygyver-0.1.1.42.dist-info/WHEEL
pygyver-0.1.1.42.dist-info/top_level.txt
pygyver-0.1.1.42.dist-info/RECORD
