Metadata-Version: 2.1
Name: pygyver
Version: 0.1.1.42
Summary: Data engineering & Data science Pipeline Framework
Home-page: https://github.com/madedotcom/pygyver
Author: Simone Fiorentini
Author-email: analytics@made.com
Classifier: Programming Language :: Python :: 3
Classifier: Natural Language :: English
Classifier: License :: OSI Approved :: MIT License
Classifier: Operating System :: OS Independent
Requires-Python: >=3.6
License-File: LICENSE
Requires-Dist: boto3 (>=1.9.218)
Requires-Dist: codecov (>=2.1.0)
Requires-Dist: facebook-business (>=6.0.0)
Requires-Dist: google-cloud-bigquery (>=1.24.0)
Requires-Dist: google-cloud-bigquery-datatransfer (>=3.7.0)
Requires-Dist: google-cloud-storage (>=1.28.0)
Requires-Dist: gspread (>=3.1.0)
Requires-Dist: gspread-dataframe (>=3.0.4)
Requires-Dist: moto (>=1.3.14)
Requires-Dist: nltk (>=3.4.0)
Requires-Dist: numpy (>=1.13.3)
Requires-Dist: pandas (>=1.0.0)
Requires-Dist: pandas-gbq (>=0.9.0)
Requires-Dist: pg8000 (>=1.14.0)
Requires-Dist: pyarrow (>=1.0.0)
Requires-Dist: pymysql (>=0.9.3)
Requires-Dist: pytest (>=5.3.1)
Requires-Dist: PyYAML (>=5.1)
Requires-Dist: slack-sdk (>=3.18.1)
Requires-Dist: sqlalchemy (>=1.3.0)
Requires-Dist: tox (>=3.15.0)
Requires-Dist: versioneer (>=0.18)
Requires-Dist: wheel (>=0.33.1)
